{"assets":{"82CF2F673425A7980F0C86E1D70C9121":{"type":"texture","index":2,"assetRequest":{"type":"slide","state":"contents","slide":"none"},"url":{"native":"assets\/9C3F3D6A-640E-41A4-BCA0-A8A6643BA80C.pdf"},"width":1388,"height":276},"BA246112B982F2C00BB10B3344821994":{"type":"texture","index":0,"assetRequest":{"type":"slide","state":"contents","slide":"none"},"url":{"native":"assets\/9C3F3D6A-640E-41A4-BCA0-A8A6643BA80C.pdf"},"width":1920,"height":1080},"F2066971930388E465D2591D616493FA":{"type":"texture","index":1,"assetRequest":{"type":"slide","state":"contents","slide":"none"},"url":{"native":"assets\/9C3F3D6A-640E-41A4-BCA0-A8A6643BA80C.pdf"},"width":988,"height":138},"BFD7751383149E26E71B30B25BD721A3":{"type":"texture","index":3,"assetRequest":{"type":"slide","state":"contents","slide":"none"},"url":{"native":"assets\/9C3F3D6A-640E-41A4-BCA0-A8A6643BA80C.pdf"},"width":1457,"height":109},"533A88A1F98585D5ED33DA85D8D10C0F":{"type":"texture","index":4,"assetRequest":{"type":"slide","state":"contents","slide":"none"},"url":{"native":"assets\/9C3F3D6A-640E-41A4-BCA0-A8A6643BA80C.pdf"},"width":1920,"height":1080},"E2A9BF9F302D7BB8B1CBCB0EFAE1F7D1":{"type":"texture","index":5,"assetRequest":{"type":"slide","state":"contents","slide":"none"},"url":{"native":"assets\/9C3F3D6A-640E-41A4-BCA0-A8A6643BA80C.pdf"},"width":1920,"height":1080}},"events":[{"effects":[{"beginTime":0,"baseLayer":{"animations":[],"initialState":{"affineTransform":[1,0,0,1,0,0],"masksToBounds":false,"rotation":0,"scale":1,"position":{"pointX":835,"pointY":570},"width":1388,"sublayerTransform":[1,0,0,0,0,1,0,0,0,0,1,0,0,0,0,1],"contentsRect":{"y":0,"x":0,"width":1,"height":1},"opacity":1,"edgeAntialiasingMask":251658240,"height":566,"hidden":false,"anchorPoint":{"pointX":0.5,"pointY":0.5}},"objectID":"0327D4E9-6478-4A09-A037-C44F97881A16","layers":[{"animations":[],"initialState":{"affineTransform":[1,0,0,1,0,0],"masksToBounds":false,"rotation":0,"scale":1,"position":{"pointX":819,"pointY":253},"width":1388,"sublayerTransform":[1,0,0,0,0,1,0,0,0,0,1,-0.00035007912466775983,0,0,0,1],"contentsRect":{"y":0,"x":0,"width":1,"height":1},"opacity":1,"edgeAntialiasingMask":251658240,"height":566,"hidden":false,"anchorPoint":{"pointX":0.59005763688760804,"pointY":0.44699646643109542}},"layers":[{"animations":[{"additive":false,"timeOffset":0,"beginTime":1e-100,"repeatCount":0,"fillMode":"both","duration":1,"autoreverses":false,"animations":[{"additive":false,"timeOffset":0,"beginTime":0,"from":{"scalar":false},"repeatCount":0,"fillMode":"forwards","duration":1,"autoreverses":false,"property":"hidden","to":{"scalar":false},"removedOnCompletion":true},{"repeatCount":0,"removedOnCompletion":true,"from":{"scalar":0.01},"timingFunction":"EaseOut","additive":false,"timeOffset":0,"autoreverses":false,"property":"transform.scale.xy","fillMode":"both","duration":1,"beginTime":0,"to":{"scalar":1}},{"additive":false,"timeOffset":0,"beginTime":0,"from":{"scalar":0},"repeatCount":0,"fillMode":"both","duration":1,"autoreverses":false,"property":"opacity","to":{"scalar":1},"removedOnCompletion":true},{"additive":false,"timeOffset":0,"beginTime":0,"from":{"pointX":0.5,"pointY":0.5},"repeatCount":0,"fillMode":"removed","duration":1,"autoreverses":false,"property":"anchorPoint","to":{"pointX":0.5,"pointY":0.5},"removedOnCompletion":true},{"additive":false,"timeOffset":0,"beginTime":0,"from":{"scalar":0},"repeatCount":0,"fillMode":"removed","duration":1,"autoreverses":false,"property":"transform.translation.x","to":{"scalar":0},"removedOnCompletion":true},{"additive":false,"timeOffset":0,"beginTime":0,"from":{"scalar":0},"repeatCount":0,"fillMode":"removed","duration":1,"autoreverses":false,"property":"transform.translation.y","to":{"scalar":0},"removedOnCompletion":true}],"removedOnCompletion":false}],"layers":[],"texturedRectangle":{"singleTextureOpacity":1,"textXHeight":0.19744927536231882,"textBaseline":0.9802912119506062,"isBackgroundTexture":false,"isVerticalText":false,"textColor":[0.9994240403175354,0.98555368185043335,0,1],"textureType":6},"initialState":{"affineTransform":[1,0,0,1,0,0],"masksToBounds":false,"rotation":0,"scale":1,"position":{"pointX":499,"pointY":139},"width":988,"sublayerTransform":[1,0,0,0,0,1,0,0,0,0,1,0,0,0,0,1],"contentsRect":{"y":0,"x":0,"width":1,"height":1},"opacity":1,"edgeAntialiasingMask":0,"height":138,"hidden":true,"anchorPoint":{"pointX":0.5,"pointY":0.5}},"texture":"F2066971930388E465D2591D616493FA"}]},{"animations":[],"layers":[],"texturedRectangle":{"singleTextureOpacity":1,"textXHeight":0.098724637681159411,"textBaseline":0.9615224152803421,"isBackgroundTexture":false,"isVerticalText":false,"textColor":[0.9994240403175354,0.98555368185043335,0,1],"textureType":6},"initialState":{"affineTransform":[1,0,0,1,0,0],"masksToBounds":false,"rotation":0,"scale":1,"position":{"pointX":699,"pointY":498},"width":1388,"sublayerTransform":[1,0,0,0,0,1,0,0,0,0,1,0,0,0,0,1],"contentsRect":{"y":0,"x":0,"width":1,"height":1},"opacity":1,"edgeAntialiasingMask":0,"height":276,"hidden":true,"anchorPoint":{"pointX":0.5,"pointY":0.5}},"texture":"82CF2F673425A7980F0C86E1D70C9121"}]},"effects":[],"duration":1,"type":"buildIn","attributes":{"direction":43},"name":"apple:zoom character","objectID":"0327D4E9-6478-4A09-A037-C44F97881A16"}],"automaticPlay":false,"hyperlinks":[],"accessibility":[{"text":"Sovemedisiner – indikasjoner","targetRectangle":{"y":96,"x":229.25200000000007,"width":1462.4960000000001,"height":134}}],"baseLayer":{"animations":[],"initialState":{"affineTransform":[1,0,0,1,0,0],"masksToBounds":false,"rotation":0,"scale":1,"position":{"pointX":960,"pointY":540},"width":1920,"sublayerTransform":[1,0,0,0,0,1,0,0,0,0,1,0,0,0,0,1],"contentsRect":{"y":0,"x":0,"width":1,"height":1},"opacity":1,"edgeAntialiasingMask":251658240,"height":1080,"hidden":false,"anchorPoint":{"pointX":0.5,"pointY":0.5}},"layers":[{"animations":[],"initialState":{"affineTransform":[1,0,0,1,0,0],"masksToBounds":false,"rotation":0,"scale":1,"position":{"pointX":960,"pointY":540},"width":1920,"sublayerTransform":[1,0,0,0,0,1,0,0,0,0,1,0,0,0,0,1],"contentsRect":{"y":0,"x":0,"width":1,"height":1},"opacity":1,"edgeAntialiasingMask":251658240,"height":1080,"hidden":false,"anchorPoint":{"pointX":0.5,"pointY":0.5}},"layers":[{"animations":[],"initialState":{"affineTransform":[1,0,0,1,0,0],"masksToBounds":false,"rotation":0,"scale":1,"position":{"pointX":960,"pointY":540},"width":1920,"sublayerTransform":[1,0,0,0,0,1,0,0,0,0,1,0,0,0,0,1],"contentsRect":{"y":0,"x":0,"width":1,"height":1},"opacity":1,"edgeAntialiasingMask":251658240,"height":1080,"hidden":false,"anchorPoint":{"pointX":0.5,"pointY":0.5}},"layers":[{"animations":[],"layers":[],"texturedRectangle":{"isBackgroundTexture":true,"singleTextureOpacity":1,"textureType":1,"textBaseline":0,"textXHeight":0,"isVerticalText":false},"initialState":{"affineTransform":[1,0,0,1,0,0],"masksToBounds":false,"rotation":0,"scale":1,"position":{"pointX":960,"pointY":540},"width":1920,"sublayerTransform":[1,0,0,0,0,1,0,0,0,0,1,0,0,0,0,1],"contentsRect":{"y":0,"x":0,"width":1,"height":1},"opacity":1,"edgeAntialiasingMask":0,"height":1080,"hidden":false,"anchorPoint":{"pointX":0.5,"pointY":0.5}},"texture":"BA246112B982F2C00BB10B3344821994"}]}]},{"animations":[],"initialState":{"affineTransform":[1,0,0,1,0,0],"masksToBounds":false,"rotation":0,"scale":1,"position":{"pointX":960,"pointY":540},"width":1920,"sublayerTransform":[1,0,0,0,0,1,0,0,0,0,1,0,0,0,0,1],"contentsRect":{"y":0,"x":0,"width":1,"height":1},"opacity":1,"edgeAntialiasingMask":251658240,"height":1080,"hidden":false,"anchorPoint":{"pointX":0.5,"pointY":0.5}},"layers":[{"animations":[],"initialState":{"affineTransform":[1,0,0,1,0,0],"masksToBounds":false,"rotation":0,"scale":1,"position":{"pointX":835,"pointY":570},"width":1388,"sublayerTransform":[1,0,0,0,0,1,0,0,0,0,1,0,0,0,0,1],"contentsRect":{"y":0,"x":0,"width":1,"height":1},"opacity":1,"edgeAntialiasingMask":251658240,"height":566,"hidden":false,"anchorPoint":{"pointX":0.5,"pointY":0.5}},"objectID":"0327D4E9-6478-4A09-A037-C44F97881A16","layers":[{"animations":[],"layers":[],"texturedRectangle":{"singleTextureOpacity":1,"textXHeight":0.19744927536231882,"textBaseline":0.9802912119506062,"isBackgroundTexture":false,"isVerticalText":false,"textColor":[0.9994240403175354,0.98555368185043335,0,1],"textureType":6},"initialState":{"affineTransform":[1,0,0,1,0,0],"masksToBounds":false,"rotation":0,"scale":1,"position":{"pointX":499,"pointY":139},"width":988,"sublayerTransform":[1,0,0,0,0,1,0,0,0,0,1,0,0,0,0,1],"contentsRect":{"y":0,"x":0,"width":1,"height":1},"opacity":1,"edgeAntialiasingMask":0,"height":138,"hidden":true,"anchorPoint":{"pointX":0.5,"pointY":0.5}},"texture":"F2066971930388E465D2591D616493FA"},{"animations":[],"layers":[],"texturedRectangle":{"singleTextureOpacity":1,"textXHeight":0.098724637681159411,"textBaseline":0.9615224152803421,"isBackgroundTexture":false,"isVerticalText":false,"textColor":[0.9994240403175354,0.98555368185043335,0,1],"textureType":6},"initialState":{"affineTransform":[1,0,0,1,0,0],"masksToBounds":false,"rotation":0,"scale":1,"position":{"pointX":699,"pointY":498},"width":1388,"sublayerTransform":[1,0,0,0,0,1,0,0,0,0,1,0,0,0,0,1],"contentsRect":{"y":0,"x":0,"width":1,"height":1},"opacity":1,"edgeAntialiasingMask":0,"height":276,"hidden":true,"anchorPoint":{"pointX":0.5,"pointY":0.5}},"texture":"82CF2F673425A7980F0C86E1D70C9121"}]}]},{"animations":[],"initialState":{"affineTransform":[1,0,0,1,0,0],"masksToBounds":false,"rotation":0,"scale":1,"position":{"pointX":960,"pointY":540},"width":1920,"sublayerTransform":[1,0,0,0,0,1,0,0,0,0,1,0,0,0,0,1],"contentsRect":{"y":0,"x":0,"width":1,"height":1},"opacity":1,"edgeAntialiasingMask":251658240,"height":1080,"hidden":false,"anchorPoint":{"pointX":0.5,"pointY":0.5}},"layers":[{"animations":[],"initialState":{"affineTransform":[1,0,0,1,0,0],"masksToBounds":false,"rotation":0,"scale":1,"position":{"pointX":869.5,"pointY":99.5},"width":1457,"sublayerTransform":[1,0,0,0,0,1,0,0,0,0,1,0,0,0,0,1],"contentsRect":{"y":0,"x":0,"width":1,"height":1},"opacity":1,"edgeAntialiasingMask":251658240,"height":109,"hidden":false,"anchorPoint":{"pointX":0.5,"pointY":0.5}},"layers":[{"animations":[],"layers":[],"texturedRectangle":{"singleTextureOpacity":1,"textXHeight":0.53842201834862391,"textBaseline":0.77284842674885323,"isBackgroundTexture":true,"isVerticalText":false,"textColor":[1,1,1,1],"textureType":6},"initialState":{"affineTransform":[1,0,0,1,0,0],"masksToBounds":false,"rotation":0,"scale":1,"position":{"pointX":820.5,"pointY":129.5},"width":1457,"sublayerTransform":[1,0,0,0,0,1,0,0,0,0,1,0,0,0,0,1],"contentsRect":{"y":0,"x":0,"width":1,"height":1},"opacity":1,"edgeAntialiasingMask":0,"height":109,"hidden":false,"anchorPoint":{"pointX":0.5,"pointY":0.5}},"texture":"BFD7751383149E26E71B30B25BD721A3"}]}]}]}},{"effects":[{"beginTime":0,"baseLayer":{"animations":[],"initialState":{"affineTransform":[1,0,0,1,0,0],"masksToBounds":false,"rotation":0,"scale":1,"position":{"pointX":835,"pointY":570},"width":1388,"sublayerTransform":[1,0,0,0,0,1,0,0,0,0,1,0,0,0,0,1],"contentsRect":{"y":0,"x":0,"width":1,"height":1},"opacity":1,"edgeAntialiasingMask":251658240,"height":566,"hidden":false,"anchorPoint":{"pointX":0.5,"pointY":0.5}},"objectID":"0327D4E9-6478-4A09-A037-C44F97881A16","layers":[{"animations":[],"layers":[],"texturedRectangle":{"singleTextureOpacity":1,"textXHeight":0.19744927536231882,"textBaseline":0.9802912119506062,"isBackgroundTexture":false,"isVerticalText":false,"textColor":[0.9994240403175354,0.98555368185043335,0,1],"textureType":6},"initialState":{"affineTransform":[1,0,0,1,0,0],"masksToBounds":false,"rotation":0,"scale":1,"position":{"pointX":499,"pointY":139},"width":988,"sublayerTransform":[1,0,0,0,0,1,0,0,0,0,1,0,0,0,0,1],"contentsRect":{"y":0,"x":0,"width":1,"height":1},"opacity":1,"edgeAntialiasingMask":0,"height":138,"hidden":false,"anchorPoint":{"pointX":0.5,"pointY":0.5}},"texture":"F2066971930388E465D2591D616493FA"},{"animations":[],"initialState":{"affineTransform":[1,0,0,1,0,0],"masksToBounds":false,"rotation":0,"scale":1,"position":{"pointX":819,"pointY":253},"width":1388,"sublayerTransform":[1,0,0,0,0,1,0,0,0,0,1,-0.00035007912466775983,0,0,0,1],"contentsRect":{"y":0,"x":0,"width":1,"height":1},"opacity":1,"edgeAntialiasingMask":251658240,"height":566,"hidden":false,"anchorPoint":{"pointX":0.59005763688760804,"pointY":0.44699646643109542}},"layers":[{"animations":[{"additive":false,"timeOffset":0,"beginTime":1e-100,"repeatCount":0,"fillMode":"both","duration":1,"autoreverses":false,"animations":[{"additive":false,"timeOffset":0,"beginTime":0,"from":{"scalar":false},"repeatCount":0,"fillMode":"forwards","duration":1,"autoreverses":false,"property":"hidden","to":{"scalar":false},"removedOnCompletion":true},{"repeatCount":0,"removedOnCompletion":true,"from":{"scalar":0.01},"timingFunction":"EaseOut","additive":false,"timeOffset":0,"autoreverses":false,"property":"transform.scale.xy","fillMode":"both","duration":1,"beginTime":0,"to":{"scalar":1}},{"additive":false,"timeOffset":0,"beginTime":0,"from":{"scalar":0},"repeatCount":0,"fillMode":"both","duration":1,"autoreverses":false,"property":"opacity","to":{"scalar":1},"removedOnCompletion":true},{"additive":false,"timeOffset":0,"beginTime":0,"from":{"pointX":0.5,"pointY":0.5},"repeatCount":0,"fillMode":"removed","duration":1,"autoreverses":false,"property":"anchorPoint","to":{"pointX":0.5,"pointY":0.5},"removedOnCompletion":true},{"additive":false,"timeOffset":0,"beginTime":0,"from":{"scalar":0},"repeatCount":0,"fillMode":"removed","duration":1,"autoreverses":false,"property":"transform.translation.x","to":{"scalar":0},"removedOnCompletion":true},{"additive":false,"timeOffset":0,"beginTime":0,"from":{"scalar":0},"repeatCount":0,"fillMode":"removed","duration":1,"autoreverses":false,"property":"transform.translation.y","to":{"scalar":0},"removedOnCompletion":true}],"removedOnCompletion":false}],"layers":[],"texturedRectangle":{"singleTextureOpacity":1,"textXHeight":0.098724637681159411,"textBaseline":0.9615224152803421,"isBackgroundTexture":false,"isVerticalText":false,"textColor":[0.9994240403175354,0.98555368185043335,0,1],"textureType":6},"initialState":{"affineTransform":[1,0,0,1,0,0],"masksToBounds":false,"rotation":0,"scale":1,"position":{"pointX":699,"pointY":498},"width":1388,"sublayerTransform":[1,0,0,0,0,1,0,0,0,0,1,0,0,0,0,1],"contentsRect":{"y":0,"x":0,"width":1,"height":1},"opacity":1,"edgeAntialiasingMask":0,"height":276,"hidden":true,"anchorPoint":{"pointX":0.5,"pointY":0.5}},"texture":"82CF2F673425A7980F0C86E1D70C9121"}]}]},"effects":[],"duration":1,"type":"buildIn","attributes":{"direction":43},"name":"apple:zoom character","objectID":"0327D4E9-6478-4A09-A037-C44F97881A16"}],"automaticPlay":false,"hyperlinks":[],"accessibility":[{"text":"Sovemedisiner – indikasjoner","targetRectangle":{"y":96,"x":229.25200000000007,"width":1462.4960000000001,"height":134}}],"baseLayer":{"animations":[],"initialState":{"affineTransform":[1,0,0,1,0,0],"masksToBounds":false,"rotation":0,"scale":1,"position":{"pointX":960,"pointY":540},"width":1920,"sublayerTransform":[1,0,0,0,0,1,0,0,0,0,1,0,0,0,0,1],"contentsRect":{"y":0,"x":0,"width":1,"height":1},"opacity":1,"edgeAntialiasingMask":251658240,"height":1080,"hidden":false,"anchorPoint":{"pointX":0.5,"pointY":0.5}},"layers":[{"animations":[],"initialState":{"affineTransform":[1,0,0,1,0,0],"masksToBounds":false,"rotation":0,"scale":1,"position":{"pointX":960,"pointY":540},"width":1920,"sublayerTransform":[1,0,0,0,0,1,0,0,0,0,1,0,0,0,0,1],"contentsRect":{"y":0,"x":0,"width":1,"height":1},"opacity":1,"edgeAntialiasingMask":251658240,"height":1080,"hidden":false,"anchorPoint":{"pointX":0.5,"pointY":0.5}},"layers":[{"animations":[],"initialState":{"affineTransform":[1,0,0,1,0,0],"masksToBounds":false,"rotation":0,"scale":1,"position":{"pointX":960,"pointY":540},"width":1920,"sublayerTransform":[1,0,0,0,0,1,0,0,0,0,1,0,0,0,0,1],"contentsRect":{"y":0,"x":0,"width":1,"height":1},"opacity":1,"edgeAntialiasingMask":251658240,"height":1080,"hidden":false,"anchorPoint":{"pointX":0.5,"pointY":0.5}},"layers":[{"animations":[],"layers":[],"texturedRectangle":{"isBackgroundTexture":true,"singleTextureOpacity":1,"textureType":1,"textBaseline":0,"textXHeight":0,"isVerticalText":false},"initialState":{"affineTransform":[1,0,0,1,0,0],"masksToBounds":false,"rotation":0,"scale":1,"position":{"pointX":960,"pointY":540},"width":1920,"sublayerTransform":[1,0,0,0,0,1,0,0,0,0,1,0,0,0,0,1],"contentsRect":{"y":0,"x":0,"width":1,"height":1},"opacity":1,"edgeAntialiasingMask":0,"height":1080,"hidden":false,"anchorPoint":{"pointX":0.5,"pointY":0.5}},"texture":"BA246112B982F2C00BB10B3344821994"}]}]},{"animations":[],"initialState":{"affineTransform":[1,0,0,1,0,0],"masksToBounds":false,"rotation":0,"scale":1,"position":{"pointX":960,"pointY":540},"width":1920,"sublayerTransform":[1,0,0,0,0,1,0,0,0,0,1,0,0,0,0,1],"contentsRect":{"y":0,"x":0,"width":1,"height":1},"opacity":1,"edgeAntialiasingMask":251658240,"height":1080,"hidden":false,"anchorPoint":{"pointX":0.5,"pointY":0.5}},"layers":[{"animations":[],"initialState":{"affineTransform":[1,0,0,1,0,0],"masksToBounds":false,"rotation":0,"scale":1,"position":{"pointX":835,"pointY":570},"width":1388,"sublayerTransform":[1,0,0,0,0,1,0,0,0,0,1,0,0,0,0,1],"contentsRect":{"y":0,"x":0,"width":1,"height":1},"opacity":1,"edgeAntialiasingMask":251658240,"height":566,"hidden":false,"anchorPoint":{"pointX":0.5,"pointY":0.5}},"objectID":"0327D4E9-6478-4A09-A037-C44F97881A16","layers":[{"animations":[],"layers":[],"texturedRectangle":{"singleTextureOpacity":1,"textXHeight":0.19744927536231882,"textBaseline":0.9802912119506062,"isBackgroundTexture":false,"isVerticalText":false,"textColor":[0.9994240403175354,0.98555368185043335,0,1],"textureType":6},"initialState":{"affineTransform":[1,0,0,1,0,0],"masksToBounds":false,"rotation":0,"scale":1,"position":{"pointX":499,"pointY":139},"width":988,"sublayerTransform":[1,0,0,0,0,1,0,0,0,0,1,0,0,0,0,1],"contentsRect":{"y":0,"x":0,"width":1,"height":1},"opacity":1,"edgeAntialiasingMask":0,"height":138,"hidden":false,"anchorPoint":{"pointX":0.5,"pointY":0.5}},"texture":"F2066971930388E465D2591D616493FA"},{"animations":[],"layers":[],"texturedRectangle":{"singleTextureOpacity":1,"textXHeight":0.098724637681159411,"textBaseline":0.9615224152803421,"isBackgroundTexture":false,"isVerticalText":false,"textColor":[0.9994240403175354,0.98555368185043335,0,1],"textureType":6},"initialState":{"affineTransform":[1,0,0,1,0,0],"masksToBounds":false,"rotation":0,"scale":1,"position":{"pointX":699,"pointY":498},"width":1388,"sublayerTransform":[1,0,0,0,0,1,0,0,0,0,1,0,0,0,0,1],"contentsRect":{"y":0,"x":0,"width":1,"height":1},"opacity":1,"edgeAntialiasingMask":0,"height":276,"hidden":true,"anchorPoint":{"pointX":0.5,"pointY":0.5}},"texture":"82CF2F673425A7980F0C86E1D70C9121"}]}]},{"animations":[],"initialState":{"affineTransform":[1,0,0,1,0,0],"masksToBounds":false,"rotation":0,"scale":1,"position":{"pointX":960,"pointY":540},"width":1920,"sublayerTransform":[1,0,0,0,0,1,0,0,0,0,1,0,0,0,0,1],"contentsRect":{"y":0,"x":0,"width":1,"height":1},"opacity":1,"edgeAntialiasingMask":251658240,"height":1080,"hidden":false,"anchorPoint":{"pointX":0.5,"pointY":0.5}},"layers":[{"animations":[],"initialState":{"affineTransform":[1,0,0,1,0,0],"masksToBounds":false,"rotation":0,"scale":1,"position":{"pointX":869.5,"pointY":99.5},"width":1457,"sublayerTransform":[1,0,0,0,0,1,0,0,0,0,1,0,0,0,0,1],"contentsRect":{"y":0,"x":0,"width":1,"height":1},"opacity":1,"edgeAntialiasingMask":251658240,"height":109,"hidden":false,"anchorPoint":{"pointX":0.5,"pointY":0.5}},"layers":[{"animations":[],"layers":[],"texturedRectangle":{"singleTextureOpacity":1,"textXHeight":0.53842201834862391,"textBaseline":0.77284842674885323,"isBackgroundTexture":true,"isVerticalText":false,"textColor":[1,1,1,1],"textureType":6},"initialState":{"affineTransform":[1,0,0,1,0,0],"masksToBounds":false,"rotation":0,"scale":1,"position":{"pointX":820.5,"pointY":129.5},"width":1457,"sublayerTransform":[1,0,0,0,0,1,0,0,0,0,1,0,0,0,0,1],"contentsRect":{"y":0,"x":0,"width":1,"height":1},"opacity":1,"edgeAntialiasingMask":0,"height":109,"hidden":false,"anchorPoint":{"pointX":0.5,"pointY":0.5}},"texture":"BFD7751383149E26E71B30B25BD721A3"}]}]}]}},{"effects":[{"beginTime":0,"baseLayer":{"animations":[],"initialState":{"affineTransform":[1,0,0,1,0,0],"masksToBounds":false,"rotation":0,"scale":1,"position":{"pointX":960,"pointY":540},"width":1920,"sublayerTransform":[1,0,0,0,0,1,0,0,0,0,1,0,0,0,0,1],"contentsRect":{"y":0,"x":0,"width":1,"height":1},"opacity":1,"edgeAntialiasingMask":251658240,"height":1080,"hidden":false,"anchorPoint":{"pointX":0.5,"pointY":0.5}},"objectID":"0","layers":[{"animations":[],"initialState":{"affineTransform":[1,0,0,1,0,0],"masksToBounds":false,"rotation":0,"scale":1,"position":{"pointX":960,"pointY":540},"width":1920,"sublayerTransform":[1,0,0,0,0,1,0,0,0,0,1,-0.00035007912466775983,0,0,0,1],"contentsRect":{"y":0,"x":0,"width":1,"height":1},"opacity":1,"edgeAntialiasingMask":251658240,"height":1080,"hidden":false,"anchorPoint":{"pointX":0.5,"pointY":0.5}},"layers":[{"animations":[],"layers":[],"texturedRectangle":{"isBackgroundTexture":false,"singleTextureOpacity":1,"textureType":0,"textBaseline":0,"textXHeight":0,"isVerticalText":false},"initialState":{"affineTransform":[1,0,0,1,0,0],"masksToBounds":false,"rotation":0,"scale":1,"position":{"pointX":960,"pointY":540},"width":1920,"sublayerTransform":[1,0,0,0,0,1,0,0,0,0,1,0,0,0,0,1],"contentsRect":{"y":0,"x":0,"width":1,"height":1},"opacity":1,"edgeAntialiasingMask":0,"height":1080,"hidden":false,"anchorPoint":{"pointX":0.5,"pointY":0.5}},"texture":"E2A9BF9F302D7BB8B1CBCB0EFAE1F7D1"},{"animations":[{"additive":false,"timeOffset":0,"beginTime":0,"repeatCount":0,"fillMode":"both","duration":1.5,"autoreverses":false,"animations":[{"additive":false,"timeOffset":0,"beginTime":0,"from":{"scalar":1},"repeatCount":0,"fillMode":"removed","duration":1.5,"autoreverses":false,"property":"transform.translation.z","to":{"scalar":1},"removedOnCompletion":true},{"repeatCount":0,"timingControlPoint2y":0.087685436010360718,"removedOnCompletion":true,"from":{"scalar":0},"timingFunction":"custom","additive":false,"timeOffset":0,"autoreverses":false,"timingControlPoint1x":0.3746802806854248,"fillMode":"removed","property":"transform.translation.x","duration":1.5,"beginTime":0,"timingControlPoint2x":0.4752049446105957,"timingControlPoint1y":0,"to":{"scalar":0}},{"repeatCount":0,"timingControlPoint2y":0.087685436010360718,"removedOnCompletion":true,"from":{"scalar":0},"timingFunction":"custom","additive":false,"timeOffset":0,"autoreverses":false,"timingControlPoint1x":0.3746802806854248,"fillMode":"removed","property":"transform.translation.y","duration":1.5,"beginTime":0,"timingControlPoint2x":0.4752049446105957,"timingControlPoint1y":0,"to":{"scalar":-1080}}],"removedOnCompletion":false}],"layers":[],"texturedRectangle":{"isBackgroundTexture":false,"singleTextureOpacity":1,"textureType":0,"textBaseline":0,"textXHeight":0,"isVerticalText":false},"initialState":{"affineTransform":[1,0,0,1,0,0],"masksToBounds":false,"rotation":0,"scale":1,"position":{"pointX":960,"pointY":540},"width":1920,"sublayerTransform":[1,0,0,0,0,1,0,0,0,0,1,0,0,0,0,1],"contentsRect":{"y":0,"x":0,"width":1,"height":1},"opacity":1,"edgeAntialiasingMask":0,"height":1080,"hidden":false,"anchorPoint":{"pointX":0.5,"pointY":0.5}},"texture":"533A88A1F98585D5ED33DA85D8D10C0F"}]}]},"effects":[],"duration":1.5,"type":"transition","attributes":{"direction":14},"name":"apple:reveal","objectID":"0"}],"automaticPlay":false,"hyperlinks":[],"accessibility":[{"text":"Sovemedisiner – indikasjoner","targetRectangle":{"y":96,"x":229.25200000000007,"width":1462.4960000000001,"height":134}},{"text":"Akutt, situasjonsbetinget insomni (kriser)","targetRectangle":{"y":347,"x":193.00000023841858,"width":939.12000000000035,"height":62}},{"text":"Imovane el. Stilnoct i maks. 2 – 3 uker","targetRectangle":{"y":390.3999992609024,"x":233.61535716056824,"width":740.95999999999958,"height":246.09999936819077}},{"text":"Kroniske søvnvansker – ikke dokumentasjon. Kan forverre","targetRectangle":{"y":636.49999862909317,"x":193.00000023841858,"width":1339.0520000000001,"height":62}},{"text":"Ev. Remeron 15 mg; Tolvon 2,5 mg; Surmontil 5-10 mg","targetRectangle":{"y":698.49999862909317,"x":241.00000524520874,"width":1067.7479999999994,"height":112}},{"text":"Evt. Circadin 2 mg (Melatonin 3 mg for døgnrytme)","targetRectangle":{"y":810.49999862909317,"x":241.00000524520874,"width":997.52399999999966,"height":112}}],"baseLayer":{"animations":[],"initialState":{"affineTransform":[1,0,0,1,0,0],"masksToBounds":false,"rotation":0,"scale":1,"position":{"pointX":960,"pointY":540},"width":1920,"sublayerTransform":[1,0,0,0,0,1,0,0,0,0,1,0,0,0,0,1],"contentsRect":{"y":0,"x":0,"width":1,"height":1},"opacity":1,"edgeAntialiasingMask":251658240,"height":1080,"hidden":false,"anchorPoint":{"pointX":0.5,"pointY":0.5}},"objectID":"0","layers":[{"animations":[],"initialState":{"affineTransform":[1,0,0,1,0,0],"masksToBounds":false,"rotation":0,"scale":1,"position":{"pointX":960,"pointY":540},"width":1920,"sublayerTransform":[1,0,0,0,0,1,0,0,0,0,1,-0.00035007912466775983,0,0,0,1],"contentsRect":{"y":0,"x":0,"width":1,"height":1},"opacity":1,"edgeAntialiasingMask":251658240,"height":1080,"hidden":false,"anchorPoint":{"pointX":0.5,"pointY":0.5}},"layers":[{"animations":[],"layers":[],"texturedRectangle":{"isBackgroundTexture":false,"singleTextureOpacity":1,"textureType":0,"textBaseline":0,"textXHeight":0,"isVerticalText":false},"initialState":{"affineTransform":[1,0,0,1,0,0],"masksToBounds":false,"rotation":0,"scale":1,"position":{"pointX":960,"pointY":540},"width":1920,"sublayerTransform":[1,0,0,0,0,1,0,0,0,0,1,0,0,0,0,1],"contentsRect":{"y":0,"x":0,"width":1,"height":1},"opacity":1,"edgeAntialiasingMask":0,"height":1080,"hidden":false,"anchorPoint":{"pointX":0.5,"pointY":0.5}},"texture":"533A88A1F98585D5ED33DA85D8D10C0F"}]}]}}]}